cronify/common.py
cronify/cronify.py
cronify/__init__.py
cronify-0.13.data/data/etc/init.d/cronifyd
pythonlibraries/threadpool.py
pythonlibraries/__init__.py
pythonlibraries/tests/test_threadpool.py
pythonlibraries/tests/__init__.py
cronify-0.13.dist-info/METADATA
cronify-0.13.dist-info/pbr.json
cronify-0.13.dist-info/RECORD
cronify-0.13.dist-info/metadata.json
cronify-0.13.dist-info/WHEEL
cronify-0.13.dist-info/top_level.txt
cronify-0.13.dist-info/DESCRIPTION.rst
