Metadata-Version: 2.0
Name: cronify
Version: 0.13
Summary: File event based task scheduler using the linux kernel's inotify API
Home-page: https://github.com/pkittenis/cronify
Author: Panos Kittenis
Author-email: pkittenis@gmail.com
License: GPLv2
Platform: UNKNOWN
Classifier: License :: OSI Approved :: GNU General Public License v2 (GPLv2)
Classifier: Intended Audience :: Developers
Classifier: Intended Audience :: System Administrators
Classifier: Programming Language :: Python
Classifier: Topic :: Utilities
Classifier: Operating System :: POSIX :: Linux
Classifier: Programming Language :: Python :: 2
Classifier: Programming Language :: Python :: 2.6
Classifier: Programming Language :: Python :: 2.7
Classifier: Programming Language :: Python :: 3
Classifier: Programming Language :: Python :: 3.4
Classifier: Programming Language :: Python :: 3.5
Classifier: Topic :: Utilities
Classifier: Operating System :: POSIX :: Linux
Requires-Dist: pyinotify
Requires-Dist: PyYAML
Requires-Dist: python-daemon
Requires-Dist: pytz
